{
  "created_at": "2025-12-22T18:08:04.497665",
  "model_type": "ProductionEnsemble",
  "model_file": "models/production/ensemble_basic.pkl",
  "version": "1.0.0",
  "phase": "Phase 50.9",
  "status": "production_ready",
  "feature_names": [
    "close",
    "volume",
    "rsi_14",
    "macd",
    "macd_signal",
    "macd_histogram",
    "stoch_k",
    "stoch_d",
    "atr_14",
    "bb_upper",
    "bb_lower",
    "bb_position",
    "atr_ratio",
    "ema_20",
    "ema_50",
    "volume_ratio",
    "volume_ema",
    "donchian_high_20",
    "donchian_low_20",
    "channel_position",
    "adx_14",
    "plus_di_14",
    "minus_di_14",
    "close_lag_1",
    "close_lag_2",
    "close_lag_3",
    "close_lag_10",
    "volume_lag_1",
    "volume_lag_2",
    "volume_lag_3",
    "rsi_lag_1",
    "macd_lag_1",
    "close_ma_10",
    "close_ma_20",
    "close_std_5",
    "close_std_10",
    "close_std_20",
    "rsi_x_atr",
    "macd_x_volume",
    "bb_position_x_volume_ratio",
    "close_x_atr",
    "volume_x_bb_position",
    "hour",
    "day_of_week",
    "is_market_open_hour",
    "is_europe_session",
    "hour_cos",
    "day_sin",
    "day_cos",
    "strategy_signal_ATRBased",
    "strategy_signal_DonchianChannel",
    "strategy_signal_ADXTrendStrength",
    "strategy_signal_BBReversal",
    "strategy_signal_StochasticReversal",
    "strategy_signal_MACDEMACrossover"
  ],
  "individual_models": [
    "lightgbm",
    "xgboost",
    "random_forest"
  ],
  "model_weights": {
    "lightgbm": 0.4,
    "xgboost": 0.4,
    "random_forest": 0.2
  },
  "performance_metrics": {
    "lightgbm": {
      "accuracy": 0.955607476635514,
      "f1_score": 0.9508317814461318,
      "precision": 0.9462040826585454,
      "recall": 0.955607476635514,
      "cv_f1_mean": 0.986279123540873,
      "cv_f1_std": 0.012239434643124629
    },
    "xgboost": {
      "accuracy": 0.9680685358255452,
      "f1_score": 0.9561927445273292,
      "precision": 0.9446047949259424,
      "recall": 0.9680685358255452,
      "cv_f1_mean": 0.9869493357652391,
      "cv_f1_std": 0.010839345222749756
    },
    "random_forest": {
      "accuracy": 0.9357476635514018,
      "f1_score": 0.9415235023821344,
      "precision": 0.9475194697273995,
      "recall": 0.9357476635514018,
      "cv_f1_mean": 0.9868999036347432,
      "cv_f1_std": 0.012141292678133934
    }
  },
  "training_info": {
    "samples": 17112,
    "feature_count": 55,
    "training_duration_seconds": 0
  },
  "git_info": {
    "commit": "69a87e6543f390106ed36c87a4c76218f24a6acb",
    "commit_short": "69a87e65",
    "branch": "main"
  },
  "notes": "Phase 50.9完了・外部API完全削除・62特徴量固定システム・2段階Graceful Degradation・シンプル設計回帰・TimeSeriesSplit n_splits=5・Early Stopping・SMOTE・Optuna最適化"
}