{
  "timestamp": "2025-08-13T03:20:13.404874",
  "period_hours": 24,
  "stats": {
    "total_signals": 0,
    "last_signal_time": null,
    "signal_types": {},
    "confidence_values": [],
    "anomalies": [],
    "health_score": 100
  },
  "anomalies": [
    {
      "type": "NO_SIGNALS",
      "severity": "CRITICAL",
      "message": "No signals found in CSV",
      "duration_hours": 24
    }
  ],
  "health_score": 70,
  "recommendations": [
    "\ud83d\udea8 Check if trading system is running",
    "\ud83d\udd0d Verify data feed connection",
    "\ud83d\udcca Check model loading and initialization"
  ]
}